LICENSE
MANIFEST.in
README.md
pytest_aws.py
requirements.txt
setup.py
pytest_aws.egg-info/PKG-INFO
pytest_aws.egg-info/SOURCES.txt
pytest_aws.egg-info/dependency_links.txt
pytest_aws.egg-info/entry_points.txt
pytest_aws.egg-info/requires.txt
pytest_aws.egg-info/top_level.txt