Metadata-Version: 1.1
Name: pytest-aws
Version: 0.1.0
Summary: pytest plugin for testing AWS resource configurations
Home-page: https://github.com/g-k/pytest-aws
Author: Mozilla Services
Author-email: services-dev@mozilla.com
License: Mozilla Public License 2.0
Platform: UNKNOWN
Classifier: Development Status :: 4 - Beta
Classifier: Framework :: Pytest
Classifier: Intended Audience :: Developers
Classifier: Topic :: Software Development :: Testing
Classifier: Programming Language :: Python
Classifier: Programming Language :: Python :: 2
Classifier: Programming Language :: Python :: 2.7
Classifier: Programming Language :: Python :: 3
Classifier: Programming Language :: Python :: 3.6
Classifier: Programming Language :: Python :: Implementation :: CPython
Classifier: Operating System :: OS Independent
